{"v":"4.8.0","meta":{"g":"LottieFiles AE ","a":"","k":"","d":"","tc":""},"fr":29.9700012207031,"ip":0,"op":90.0000036657751,"w":1500,"h":1500,"nm":"dog5","ddd":0,"assets":[],"layers":[{"ddd":0,"ind":1,"ty":4,"nm":"eye/dog5 Outlines","parent":2,"sr":1,"ks":{"o":{"a":0,"k":100,"ix":11},"r":{"a":0,"k":0,"ix":10},"p":{"a":0,"k":[347.5,448.5,0],"ix":2},"a":{"a":0,"k":[24,36,0],"ix":1},"s":{"a":1,"k":[{"i":{"x":[0.833,0.833,0.833],"y":[0.833,0.833,0.833]},"o":{"x":[0.167,0.167,0.167],"y":[0.167,0.167,0.167]},"t":0,"s":[100,100,100]},{"i":{"x":[0.833,0.833,0.833],"y":[0.833,0.833,0.833]},"o":{"x":[0.167,0.167,0.167],"y":[0.167,0.167,0.167]},"t":3,"s":[100,-6,100]},{"i":{"x":[0.833,0.833,0.833],"y":[0.833,0.833,0.833]},"o":{"x":[0.167,0.167,0.167],"y":[0.167,0.167,0.167]},"t":6,"s":[100,100,100]},{"i":{"x":[0.833,0.833,0.833],"y":[0.833,0.833,0.833]},"o":{"x":[0.167,0.167,0.167],"y":[0.167,0.167,0.167]},"t":63,"s":[100,100,100]},{"i":{"x":[0.833,0.833,0.833],"y":[0.833,0.833,0.833]},"o":{"x":[0.167,0.167,0.167],"y":[0.167,0.167,0.167]},"t":66,"s":[100,-6,100]},{"t":69.0000028104276,"s":[100,100,100]}],"ix":6}},"ao":0,"shapes":[{"ty":"gr","it":[{"ind":0,"ty":"sh","ix":1,"ks":{"a":0,"k":{"i":[[-22.15,-26.5],[-20.549999999999997,6.199999999999999],[-5.35,35.6],[23.450000000000003,22.7],[21.25,8.8],[17.95,-1.2000000000000002],[15.95,-11],[15.35,-16.8],[4.35,-35.599999999999994]],"o":[[-22.849999999999998,-5.800000000000001],[-15.049999999999999,28.2],[16.049999999999997,32.4],[21.55,10.4],[19.25,3.3],[16.349999999999998,-8.4],[15.95,-10],[14.049999999999999,-28.2],[-15.35,-33.599999999999994]],"v":[[-23.45,-17.8],[-16.65,17.5],[5.35,34],[21.85,12],[20.55,7.5],[16.95,-5.8],[15.35,-13.6],[15.35,-17.5],[-6.35,-34.3]],"c":true},"ix":2},"nm":"Path 1","mn":"ADBE Vector Shape - Group","hd":false,"_render":true},{"ty":"fl","c":{"a":0,"k":[0.1144,0.1096,0.1056,1],"ix":4},"o":{"a":0,"k":100,"ix":5},"r":1,"bm":0,"nm":"Fill 1","mn":"ADBE Vector Graphic - Fill","hd":false,"_render":true},{"ty":"tr","p":{"a":0,"k":[23.7,35.85],"ix":2},"a":{"a":0,"k":[0,0],"ix":1},"s":{"a":0,"k":[100,100],"ix":3},"r":{"a":0,"k":0,"ix":6},"o":{"a":0,"k":100,"ix":7},"sk":{"a":0,"k":0,"ix":4},"sa":{"a":0,"k":0,"ix":5},"nm":"Transform","_render":true}],"nm":"Group 1","np":2,"cix":2,"bm":0,"ix":1,"mn":"ADBE Vector Group","hd":false,"_render":true}],"ip":0,"op":90.0000036657751,"st":0,"bm":0,"completed":true},{"ddd":0,"ind":2,"ty":4,"nm":"head/dog5 Outlines","sr":1,"ks":{"o":{"a":0,"k":100,"ix":11},"r":{"a":1,"k":[{"i":{"x":[0.833],"y":[0.833]},"o":{"x":[0.167],"y":[0.167]},"t":0,"s":[0]},{"i":{"x":[0.833],"y":[0.833]},"o":{"x":[0.167],"y":[0.167]},"t":20,"s":[0]},{"i":{"x":[0.833],"y":[0.833]},"o":{"x":[0.167],"y":[0.167]},"t":32,"s":[-9]},{"i":{"x":[0.833],"y":[0.833]},"o":{"x":[0.167],"y":[0.167]},"t":73,"s":[-9]},{"i":{"x":[0.833],"y":[0.833]},"o":{"x":[0.167],"y":[0.167]},"t":89,"s":[0]},{"i":{"x":[0.833],"y":[0.833]},"o":{"x":[0.167],"y":[0.167]},"t":106,"s":[-9]},{"i":{"x":[0.833],"y":[0.833]},"o":{"x":[0.167],"y":[0.167]},"t":115,"s":[-9]},{"i":{"x":[0.833],"y":[0.833]},"o":{"x":[0.167],"y":[0.167]},"t":119,"s":[0]},{"t":128.000005213547,"s":[0]}],"ix":10},"p":{"a":0,"k":[746,606,0],"ix":2},"a":{"a":0,"k":[447.5,448.5,0],"ix":1},"s":{"a":0,"k":[100,100,100],"ix":6}},"ao":0,"shapes":[{"ty":"gr","it":[{"ind":0,"ty":"sh","ix":1,"ks":{"a":0,"k":{"i":[[-97.9,88.35000000000001],[80.10000000000001,-88.35]],"o":[[97.89999999999999,70.25],[-82.39999999999999,-27.25]],"v":[[-2.4,79.65],[-12.1,-53.35]],"c":true},"ix":2},"nm":"Path 1","mn":"ADBE Vector Shape - Group","hd":false,"_render":true},{"ty":"fl","c":{"a":0,"k":[0.1144,0.1096,0.1056,1],"ix":4},"o":{"a":0,"k":100,"ix":5},"r":1,"bm":0,"nm":"Fill 1","mn":"ADBE Vector Graphic - Fill","hd":false,"_render":true},{"ty":"tr","p":{"a":0,"k":[796.65,562.088],"ix":2},"a":{"a":0,"k":[0,0],"ix":1},"s":{"a":0,"k":[100,100],"ix":3},"r":{"a":0,"k":0,"ix":6},"o":{"a":0,"k":100,"ix":7},"sk":{"a":0,"k":0,"ix":4},"sa":{"a":0,"k":0,"ix":5},"nm":"Transform","_render":true}],"nm":"Group 1","np":2,"cix":2,"bm":0,"ix":1,"mn":"ADBE Vector Group","hd":false,"_render":true},{"ty":"gr","it":[{"ind":0,"ty":"sh","ix":1,"ks":{"a":0,"k":{"i":[[-94.05,-342.45],[-264.65,-290.05],[-334.84999999999997,-145.65],[270.45000000000005,342.45],[268.15000000000003,-48.55],[177.25,-138.15],[10.150000000000006,-321.05]],"o":[[-174.05,-342.15],[-331.65,-199.05],[-331.54999999999995,211.75],[308.95000000000005,-30.05],[206.05,-103.25],[95.95000000000002,-236.65],[-85.05,-341.45]],"v":[[-102.85,-342.45],[-302.15,-238.85],[-334.15,-97.05],[334.85,0.65],[238.05,-75.05],[150.05,-171.15],[-76.25,-339.55]],"c":true},"ix":2},"nm":"Path 1","mn":"ADBE Vector Shape - Group","hd":false,"_render":true},{"ty":"fl","c":{"a":0,"k":[1,0.4431,0,1],"ix":4},"o":{"a":0,"k":100,"ix":5},"r":1,"bm":0,"nm":"Fill 1","mn":"ADBE Vector Graphic - Fill","hd":false,"_render":true},{"ty":"tr","p":{"a":0,"k":[523.2,553.988],"ix":2},"a":{"a":0,"k":[0,0],"ix":1},"s":{"a":0,"k":[100,100],"ix":3},"r":{"a":0,"k":0,"ix":6},"o":{"a":0,"k":100,"ix":7},"sk":{"a":0,"k":0,"ix":4},"sa":{"a":0,"k":0,"ix":5},"nm":"Transform","_render":true}],"nm":"Group 2","np":2,"cix":2,"bm":0,"ix":2,"mn":"ADBE Vector Group","hd":false,"_render":true},{"ty":"gr","it":[{"ind":0,"ty":"sh","ix":1,"ks":{"a":0,"k":{"i":[[-78.122,76.077],[-155.054,-75.01199999999999],[166.171,-6.553000000000026]],"o":[[-116.75,-5.079999999999998],[5.282000000000011,-166.41699999999997],[138.581,166.771]],"v":[[-78.122,76.077],[-166.172,-166.771],[138.581,166.771]],"c":true},"ix":2},"nm":"Path 1","mn":"ADBE Vector Shape - Group","hd":false,"_render":true},{"ty":"fl","c":{"a":0,"k":[0.4128,0.2227,0.0672,1],"ix":4},"o":{"a":0,"k":100,"ix":5},"r":1,"bm":0,"nm":"Fill 1","mn":"ADBE Vector Graphic - Fill","hd":false,"_render":true},{"ty":"tr","p":{"a":0,"k":[401.32,167.021],"ix":2},"a":{"a":0,"k":[0,0],"ix":1},"s":{"a":0,"k":[100,100],"ix":3},"r":{"a":0,"k":0,"ix":6},"o":{"a":0,"k":100,"ix":7},"sk":{"a":0,"k":0,"ix":4},"sa":{"a":0,"k":0,"ix":5},"nm":"Transform","_render":true}],"nm":"Group 3","np":2,"cix":2,"bm":0,"ix":3,"mn":"ADBE Vector Group","hd":false,"_render":true},{"ty":"gr","it":[{"ind":0,"ty":"sh","ix":1,"ks":{"a":0,"k":{"i":[[93.75,-57.55],[-46.749999999999986,-152.45],[-18.25,174.75]],"o":[[17.950000000000003,-105.85],[-157.14999999999998,-4.550000000000011],[157.15,168.65]],"v":[[93.75,-57.55],[-136.45,-174.75],[157.15,168.65]],"c":true},"ix":2},"nm":"Path 1","mn":"ADBE Vector Shape - Group","hd":false,"_render":true},{"ty":"fl","c":{"a":0,"k":[0.4128,0.2227,0.0672,1],"ix":4},"o":{"a":0,"k":100,"ix":5},"r":1,"bm":0,"nm":"Fill 1","mn":"ADBE Vector Graphic - Fill","hd":false,"_render":true},{"ty":"tr","p":{"a":0,"k":[157.4,385.988],"ix":2},"a":{"a":0,"k":[0,0],"ix":1},"s":{"a":0,"k":[100,100],"ix":3},"r":{"a":0,"k":0,"ix":6},"o":{"a":0,"k":100,"ix":7},"sk":{"a":0,"k":0,"ix":4},"sa":{"a":0,"k":0,"ix":5},"nm":"Transform","_render":true}],"nm":"Group 4","np":2,"cix":2,"bm":0,"ix":4,"mn":"ADBE Vector Group","hd":false,"_render":true}],"ip":0,"op":90.0000036657751,"st":0,"bm":0,"completed":true},{"ddd":0,"ind":3,"ty":4,"nm":"body/dog5 Outlines","sr":1,"ks":{"o":{"a":0,"k":100,"ix":11},"r":{"a":0,"k":0,"ix":10},"p":{"a":0,"k":[750,1048,0],"ix":2},"a":{"a":0,"k":[440,391.5,0],"ix":1},"s":{"a":0,"k":[100,100,100],"ix":6}},"ao":0,"shapes":[{"ty":"gr","it":[{"ind":0,"ty":"sh","ix":1,"ks":{"a":0,"k":{"i":[[-3.5999999999999996,-115],[69.19999999999999,-105.89999999999999],[124.5,-27.599999999999998],[107.7,43.6],[145.5,73.10000000000001],[167.20000000000002,80.3],[176,84.10000000000001],[179.2,82.2],[121.9,109.3],[28.999999999999996,100.89999999999999],[-63.199999999999996,90.9],[-128.6,91.2],[-180,67.6],[-207.1,54.7],[-156.1,109.3],[-49.5,120.6],[55.39999999999999,130.6],[154.4,130.3],[207.1,75],[121.99999999999999,46.1],[145.6,-39.599999999999994],[83.8,-120.29999999999998],[18.099999999999998,-132.6]],"o":[[36.5,-117.5],[120,-59.599999999999994],[104.8,28.400000000000002],[135.8,67.6],[161.39999999999998,78.60000000000001],[174.3,83.1],[177.6,85.4],[156.6,109.6],[61.400000000000006,107.7],[-33.1,92.19999999999999],[-111.1,93.2],[-164.1,81.2],[-198.39999999999998,51.4],[-189.7,96.4],[-84.19999999999999,120.3],[21.1,126.1],[122.3,132.9],[200,96.30000000000001],[162.1,55.5],[140.39999999999998,-12.399999999999999],[115.2,-100.6],[35.6,-132.89999999999998],[-4.6,-125.30000000000001]],"v":[[3.2,-115.6],[93.8,-83.6],[113.2,4.8],[127.4,60.5],[156.2,76.7],[172.4,82.5],[177.6,85.4],[176,86],[94.4,108.7],[-3.3,96.1],[-93.3,92.2],[-145.7,86.7],[-194.2,55],[-204.6,61.1],[-120.1,114.8],[-13.9,123.5],[90.6,131.9],[180.6,110.9],[180.9,63.6],[130.7,18.3],[130.4,-70.1],[52.1,-128.7],[1.9,-127.4]],"c":true},"ix":2},"nm":"Path 1","mn":"ADBE Vector Shape - Group","hd":false,"_render":true},{"ty":"fl","c":{"a":0,"k":[0.4128,0.2227,0.0672,1],"ix":4},"o":{"a":0,"k":100,"ix":5},"r":1,"bm":0,"nm":"Fill 1","mn":"ADBE Vector Graphic - Fill","hd":false,"_render":true},{"ty":"tr","p":{"a":0,"k":[255.75,649.25],"ix":2},"a":{"a":0,"k":[0,0],"ix":1},"s":{"a":0,"k":[100,100],"ix":3},"r":{"a":0,"k":0,"ix":6},"o":{"a":0,"k":100,"ix":7},"sk":{"a":0,"k":0,"ix":4},"sa":{"a":0,"k":0,"ix":5},"nm":"Transform","_render":true}],"nm":"Group 1","np":2,"cix":2,"bm":0,"ix":1,"mn":"ADBE Vector Group","hd":false,"_render":true},{"ty":"gr","it":[{"ind":0,"ty":"sh","ix":1,"ks":{"a":0,"k":{"i":[[-7.8,-161.20000000000002],[-3.9,-50.900000000000006],[0,55.900000000000006],[-6.8,108.30000000000001],[-20.400000000000002,143.9],[-10,162.9],[-3.8000000000000003,161],[15.6,112.5],[18.8,35.8],[6.1000000000000005,-103.69999999999999]],"o":[[-14.6,-104.60000000000001],[0.6000000000000001,28.7],[-4.5,95.60000000000001],[-12.9,132.20000000000002],[-14.8,160],[-4.5,161],[15.2,150],[20.4,64.6],[12.6,-48.3],[-2,-162.89999999999998]],"v":[[-8.1,-157.4],[-1,1.8],[-2.9,82.7],[-10,120.9],[-16.1,155.5],[-5.1,161.3],[-3.2,160.7],[17.5,93.1],[16.5,7],[-1.3,-158.7]],"c":true},"ix":2},"nm":"Path 1","mn":"ADBE Vector Shape - Group","hd":false,"_render":true},{"ty":"fl","c":{"a":0,"k":[0.4128,0.2227,0.0672,1],"ix":4},"o":{"a":0,"k":100,"ix":5},"r":1,"bm":0,"nm":"Fill 1","mn":"ADBE Vector Graphic - Fill","hd":false,"_render":true},{"ty":"tr","p":{"a":0,"k":[562.25,546.65],"ix":2},"a":{"a":0,"k":[0,0],"ix":1},"s":{"a":0,"k":[100,100],"ix":3},"r":{"a":0,"k":0,"ix":6},"o":{"a":0,"k":100,"ix":7},"sk":{"a":0,"k":0,"ix":4},"sa":{"a":0,"k":0,"ix":5},"nm":"Transform","_render":true}],"nm":"Group 2","np":2,"cix":2,"bm":0,"ix":2,"mn":"ADBE Vector Group","hd":false,"_render":true},{"ty":"gr","it":[{"ind":0,"ty":"sh","ix":1,"ks":{"a":0,"k":{"i":[[-63.4,-176.2],[-68.9,8.600000000000009],[-27.2,153.7],[68.9,144.6],[51.4,106.8],[7.399999999999999,153.7],[-33.4,78.7],[-45.7,-99.6],[-61.6,-177]],"o":[[-58.9,-85.49999999999999],[-41.1,125.5],[34,177],[61.1,105.8],[40.1,142.1],[-28.5,107.1],[-46.6,-22.300000000000004],[-60.6,-176.29999999999998],[-62.7,-176.5]],"v":[[-63.1,-175.2],[-47.9,96.7],[1.6,164.7],[62.4,112.6],[49.5,112.6],[-13,127.2],[-36.6,54.1],[-60.6,-175.7],[-62.2,-176.7]],"c":true},"ix":2},"nm":"Path 1","mn":"ADBE Vector Shape - Group","hd":false,"_render":true},{"ty":"fl","c":{"a":0,"k":[0.4128,0.2227,0.0672,1],"ix":4},"o":{"a":0,"k":100,"ix":5},"r":1,"bm":0,"nm":"Fill 1","mn":"ADBE Vector Graphic - Fill","hd":false,"_render":true},{"ty":"tr","p":{"a":0,"k":[501.65,570.35],"ix":2},"a":{"a":0,"k":[0,0],"ix":1},"s":{"a":0,"k":[100,100],"ix":3},"r":{"a":0,"k":0,"ix":6},"o":{"a":0,"k":100,"ix":7},"sk":{"a":0,"k":0,"ix":4},"sa":{"a":0,"k":0,"ix":5},"nm":"Transform","_render":true}],"nm":"Group 3","np":2,"cix":2,"bm":0,"ix":3,"mn":"ADBE Vector Group","hd":false,"_render":true},{"ty":"gr","it":[{"ind":0,"ty":"sh","ix":1,"ks":{"a":0,"k":{"i":[[-164.6,-94.2],[-106.30000000000001,35.300000000000004],[28.299999999999997,121.7],[170.4,98.1],[53.2,-39.2],[-108.99999999999999,-130.8]],"o":[[-170.4,-35.6],[-27.000000000000007,103.60000000000001],[130.6,130.8],[102.4,-11],[-45.2,-93.9],[-152.7,-115.3]],"v":[[-164.6,-94.2],[-64.9,70.9],[76.5,125.9],[139.3,48.2],[-8,-73.2],[-152.7,-115.3]],"c":true},"ix":2},"nm":"Path 1","mn":"ADBE Vector Shape - Group","hd":false,"_render":true},{"ty":"fl","c":{"a":0,"k":[0.1144,0.1096,0.1056,1],"ix":4},"o":{"a":0,"k":100,"ix":5},"r":1,"bm":0,"nm":"Fill 1","mn":"ADBE Vector Graphic - Fill","hd":false,"_render":true},{"ty":"tr","p":{"a":0,"k":[456.55,169.55],"ix":2},"a":{"a":0,"k":[0,0],"ix":1},"s":{"a":0,"k":[100,100],"ix":3},"r":{"a":0,"k":0,"ix":6},"o":{"a":0,"k":100,"ix":7},"sk":{"a":0,"k":0,"ix":4},"sa":{"a":0,"k":0,"ix":5},"nm":"Transform","_render":true}],"nm":"Group 4","np":2,"cix":2,"bm":0,"ix":4,"mn":"ADBE Vector Group","hd":false,"_render":true},{"ty":"gr","it":[{"ind":0,"ty":"sh","ix":1,"ks":{"a":0,"k":{"i":[[98.4,303.2],[143.4,324.2],[73.8,373.1],[-293.59999999999997,387.3],[-181.3,29],[-44.1,-132.2],[-13.5,-327.9],[180.4,-368.4],[293.6,-184.8],[275.2,80.6],[277.8,281],[172.29999999999998,273.2],[108.89999999999999,294.90000000000003]],"o":[[109.7,317.8],[143.1,381.5],[-102.30000000000001,364],[-248.99999999999997,74],[-70.6,-88.5],[-22.3,-256.4],[102.4,-390.7],[277.8,-260.9],[255.40000000000003,-21.69999999999999],[282,216.5],[211.40000000000003,390.7],[146.4,267.7],[101.8,309.1]],"v":[[98.4,303.2],[143.4,345.9],[52.1,371.8],[-261.9,165.9],[-122.1,-33.8],[-31.5,-203.4],[39.9,-356.7],[226.3,-317.5],[277.1,-113.6],[279.7,173.5],[256.1,316.9],[162.6,250.2],[101.8,309.1]],"c":true},"ix":2},"nm":"Path 1","mn":"ADBE Vector Shape - Group","hd":false,"_render":true},{"ty":"fl","c":{"a":0,"k":[1,0.4431,0,1],"ix":4},"o":{"a":0,"k":100,"ix":5},"r":1,"bm":0,"nm":"Fill 1","mn":"ADBE Vector Graphic - Fill","hd":false,"_render":true},{"ty":"tr","p":{"a":0,"k":[293.85,390.95],"ix":2},"a":{"a":0,"k":[0,0],"ix":1},"s":{"a":0,"k":[100,100],"ix":3},"r":{"a":0,"k":0,"ix":6},"o":{"a":0,"k":100,"ix":7},"sk":{"a":0,"k":0,"ix":4},"sa":{"a":0,"k":0,"ix":5},"nm":"Transform","_render":true}],"nm":"Group 5","np":2,"cix":2,"bm":0,"ix":5,"mn":"ADBE Vector Group","hd":false,"_render":true},{"ty":"gr","it":[{"ind":0,"ty":"sh","ix":1,"ks":{"a":0,"k":{"i":[[-134.1,-104.75],[-115.7,-53.25],[50.400000000000006,-58.75],[174.6,21.25],[68.1,54.55],[-118,104.75]],"o":[[-112.69999999999999,-89.85],[-36,-2.75],[151.7,-14.05],[97.19999999999999,73.05],[-41.6,70.15],[-174.6,37.45]],"v":[[-134.1,-104.75],[-91.7,-38.35],[111.2,-31.85],[129.6,51.35],[30.9,59.75],[-174.6,37.45]],"c":true},"ix":2},"nm":"Path 1","mn":"ADBE Vector Shape - Group","hd":false,"_render":true},{"ty":"fl","c":{"a":0,"k":[1,0.4431,0,1],"ix":4},"o":{"a":0,"k":100,"ix":5},"r":1,"bm":0,"nm":"Fill 1","mn":"ADBE Vector Graphic - Fill","hd":false,"_render":true},{"ty":"tr","p":{"a":0,"k":[704.45,333.2],"ix":2},"a":{"a":0,"k":[0,0],"ix":1},"s":{"a":0,"k":[100,100],"ix":3},"r":{"a":0,"k":0,"ix":6},"o":{"a":0,"k":100,"ix":7},"sk":{"a":0,"k":0,"ix":4},"sa":{"a":0,"k":0,"ix":5},"nm":"Transform","_render":true}],"nm":"Group 6","np":2,"cix":2,"bm":0,"ix":6,"mn":"ADBE Vector Group","hd":false,"_render":true}],"ip":0,"op":90.0000036657751,"st":0,"bm":0,"completed":true},{"ddd":0,"ind":4,"ty":4,"nm":"tail/dog5 Outlines","sr":1,"ks":{"o":{"a":0,"k":100,"ix":11},"r":{"a":1,"k":[{"i":{"x":[0.833],"y":[0.833]},"o":{"x":[0.167],"y":[0.167]},"t":26,"s":[0]},{"i":{"x":[0.833],"y":[0.833]},"o":{"x":[0.167],"y":[0.167]},"t":32.5,"s":[39]},{"t":39.0000015885026,"s":[0]}],"ix":10,"x":"var $bm_rt;\n$bm_rt = loopOut('cycle', 0);"},"p":{"a":0,"k":[443.128,1306,0],"ix":2},"a":{"a":0,"k":[225,468,0],"ix":1},"s":{"a":0,"k":[100,100,100],"ix":6}},"ao":0,"shapes":[{"ty":"gr","it":[{"ind":0,"ty":"sh","ix":1,"ks":{"a":0,"k":{"i":[[39.25,123.05],[112.05,212.45],[28.85,214.95000000000002],[-48.24999999999999,139.95],[-112.05,-55.94999999999999],[-65.45,-248.55],[88.94999999999999,-228.55],[10.25,-111.25],[-6.25,11.649999999999999]],"o":[[79.65,170.95],[57.949999999999996,257.65],[-18.75,164.55],[-101.35,25.650000000000006],[-88.75,-183.45],[33.650000000000006,-257.65],[44.24999999999999,-143.64999999999998],[-14.350000000000001,-24.85],[26.65,88.15]],"v":[[64.45,152.85],[88.05,232.45],[11.65,196.55],[-67.35,98.45],[-97.45,-134.95],[-8.45,-253.75],[64.35,-181.85],[-2.05,-68.25],[11.25,52.15]],"c":true},"ix":2},"nm":"Path 1","mn":"ADBE Vector Shape - Group","hd":false,"_render":true},{"ty":"fl","c":{"a":0,"k":[0.4128,0.2227,0.0672,1],"ix":4},"o":{"a":0,"k":100,"ix":5},"r":1,"bm":0,"nm":"Fill 1","mn":"ADBE Vector Graphic - Fill","hd":false,"_render":true},{"ty":"tr","p":{"a":0,"k":[112.3,257.9],"ix":2},"a":{"a":0,"k":[0,0],"ix":1},"s":{"a":0,"k":[100,100],"ix":3},"r":{"a":0,"k":0,"ix":6},"o":{"a":0,"k":100,"ix":7},"sk":{"a":0,"k":0,"ix":4},"sa":{"a":0,"k":0,"ix":5},"nm":"Transform","_render":true}],"nm":"Group 1","np":2,"cix":2,"bm":0,"ix":1,"mn":"ADBE Vector Group","hd":false,"_render":true}],"ip":0,"op":90.0000036657751,"st":0,"bm":0,"completed":true}],"markers":[],"__complete":true}